MANIFEST.in
README.rst
requirements.txt
setup.py
hyppy/__init__.py
hyppy/func.py
hyppy/hapi.py
hyppy/parse.py
hyppy.egg-info/PKG-INFO
hyppy.egg-info/SOURCES.txt
hyppy.egg-info/dependency_links.txt
hyppy.egg-info/requires.txt
hyppy.egg-info/top_level.txt