Metadata-Version: 1.1
Name: hyppy
Version: 0.1.0
Summary: HAPI wrapper and tools for the online game Hyperiums
Home-page: https://github.com/Hypex/hyppy.git
Author: Ross Masters
Author-email: ross@rossmasters.com
License: MIT
Platform: UNKNOWN
Classifier: Development Status :: 3 - Alpha
Classifier: Intended Audience :: Developers
Classifier: License :: OSI Approved :: MIT License
Classifier: Operating System :: OS Independent
Classifier: Programming Language :: Python
Classifier: Topic :: Games/Entertainment :: Real Time Strategy
Classifier: Topic :: Software Development :: Libraries :: Python Modules
